datasette_haversine/__init__.py
datasette_haversine-0.2.1.dist-info/LICENSE
datasette_haversine-0.2.1.dist-info/METADATA
datasette_haversine-0.2.1.dist-info/WHEEL
datasette_haversine-0.2.1.dist-info/entry_points.txt
datasette_haversine-0.2.1.dist-info/top_level.txt
datasette_haversine-0.2.1.dist-info/RECORD
