Metadata-Version: 2.1
Name: datasette-haversine
Version: 0.2.1
Summary: Datasette plugin that adds a custom SQL function for haversine distances
Author: Simon Willison
License: Apache License, Version 2.0
Project-URL: Homepage, https://github.com/simonw/datasette-haversine
Project-URL: Changelog, https://github.com/simonw/datasette-haversine/releases
Project-URL: Issues, https://github.com/simonw/datasette-haversine/issues
Project-URL: CI, https://github.com/simonw/datasette-haversine/actions
Classifier: Framework :: Datasette
Classifier: License :: OSI Approved :: Apache Software License
Requires-Python: >=3.8
License-File: LICENSE
Requires-Dist: datasette
Requires-Dist: haversine
Provides-Extra: test
Requires-Dist: pytest ; extra == 'test'
